Workbook

Sheet Start Here
B2: PAY YOURSELF FIRST
B3: Canadian TFSA · FHSA · RRSP Tracker — by Maple Money Hacks
B4: Automate your payday. Never over-contribute again.
B6: Set up in 10 minutes — then let payday do the work.
B7: 1 • Setup & Dashboard — Enter the year, your names, starting balances and CRA room for Jan 1. Yellow cells only.
B8: 2 • Add your planned amount per pay for each account. Single? Leave Person 2 blank — everything still works.
B9: 3 • Cash Buckets — Set a target and a per-pay amount for each goal. All buckets live in ONE savings account, as labels.
B10: 4 • Payday Tracker — On each payday, tick Done ✓. Amounts pre-fill from Setup; change any row if a pay was different.
B11: 5 • Room Tracker — Watch FHSA / TFSA / RRSP room left. Red “OVER ROOM” warnings appear before you over-contribute.
B12: 6 • Review twice a year only — Jan 1 (new room) and Dec 31 (close the year). Automate contributions in your bank / broker app.
B14: HOW THE ROOM SYSTEM WORKS
B15: • Room = how much CRA still allows you to contribute. This tracker subtracts every payday from your Jan 1 room.
... B27: © Maple Money Hacks — Licensed for personal household use only. Not for resale or redistribution.

Sheet Setup & Dashboard
B2: SETUP & DASHBOARD — Pay Yourself First
B3: Yellow cells are yours to edit • Everything else calculates automatically • All amounts in CAD
B5: 1 — YOUR HOUSEHOLD
B6: Tracker year | C6: 2027 | D6: Enter any year — e.g. the year you are planning for.
B7: Pays per year | C7: 26 | D7: 26 = biweekly • 12 = monthly • 52 = weekly • 24 = semi-monthly
B8: Person 1 — name | C8: Person 1 | D8: Type your name here — it updates the other sheets.
B9: Person 2 — name (optional) | C9: Person 2 | D9: Single? Leave Person 2 amounts blank or $0 — the tracker still works for one person.
B10: Cash pot — starting balance (household) | D10: Total cash savings today, in ONE savings account. Allocate it across buckets in Cash Buckets.
B12: 2 — STARTING BALANCES, CRA ROOM (JAN 1) & PLANNED AMOUNT PER PAY
B13: Account | C13: Person 1 Starting Balance | D13: Person 1 CRA Room — Jan 1 | E13: Person 1 Planned / Pay | F13: Person 2 Starting Balance | G13: Person 2 CRA Room — Jan 1 | H13: Person 2 Planned / Pay
B14: TFSA
B15: FHSA
B16: RRSP
B17: Confirm CRA room in CRA My Account. FHSA room only exists if you have opened an FHSA. RRSP room is from your Notice of Assessment.
B19: 3 — YOUR GOALS (EDITABLE)
B20: Home down-payment target (household) | D20: Your target — progress is shown below.
B21: Emergency fund target (household) | D21: Your target — progress is shown below.
B22: Retirement savings goal (household) | D22: Your target — progress is shown below.
B23: FHSA lifetime cap — per person | C23: 40000 | D23: CRA FHSA lifetime maximum — do not change unless CRA changes it.
B24: Home Buyers' Plan target — per person | C24: 60000 | D24: Default $60,000 — set your own HBP goal.
B26: 4 — DASHBOARD: YOUR PROJECTED YEAR (CONTRIBUTIONS ONLY — GROWTH NOT INCLUDED)
B27: Account | C27: Person 1 Annual | D27: Person 2 Annual | E27: Household Annual | F27: Projected Dec 31 Balance | G27: Starting Balance (Household) | H27: Note
B28: TFSA | C28: =IFERROR(E14*$C$7,0) -> 0 | D28: =IFERROR(H14*$C$7,0) -> 0 | E28: =C28+D28 -> 0 | F28: =IFERROR(C14,0)+IFERROR(F14,0)+E28 -> 0 | G28: =IFERROR(C14,0)+IFERROR(F14,0) -> 0 | H28: Per-pay × pays / year
B29: FHSA | C29: =IFERROR(E15*$C$7,0) -> 0 | D29: =IFERROR(H15*$C$7,0) -> 0 | E29: =C29+D29 -> 0 | F29: =IFERROR(C15,0)+IFERROR(F15,0)+E29 -> 0 | G29: =IFERROR(C15,0)+IFERROR(F15,0) -> 0
B30: RRSP | C30: =IFERROR(E16*$C$7,0) -> 0 | D30: =IFERROR(H16*$C$7,0) -> 0 | E30: =C30+D30 -> 0 | F30: =IFERROR(C16,0)+IFERROR(F16,0)+E30 -> 0 | G30: =IFERROR(C16,0)+IFERROR(F16,0) -> 0
B31: TOTAL — Registered | C31: =SUM(C28:C30) -> 0 | D31: =SUM(D28:D30) -> 0 | E31: =SUM(E28:E30) -> 0 | F31: =SUM(F28:F30) -> 0 | G31: =SUM(G28:G30) -> 0
B32: Cash Savings | C32: =IFERROR('Cash Buckets'!F13,0) -> 0 | D32: 0 | E32: =C32 -> 0 | F32: =IFERROR(C10,0)+C32 -> 0 | G32: =IFERROR(C10,0) -> 0 | H32: From Cash Buckets
B33: TOTAL — All Savings | C33: =C31+C32 -> 0 | D33: =D31+D32 -> 0 | E33: =E31+E32 -> 0 | F33: =F31+F32 -> 0 | G33: =G31+G32 -> 0 | H33: Household total
B35: GOAL PROGRESS — PROJECTED DEC 31 vs YOUR TARGET
B36: Goal | C36: Projected | D36: Target | E36: Progress | F36: Progress Bar
B37: Home — FHSA (household) | C37: =F29 -> 0 | D37: =C20 -> 0 | E37: =IF(OR(D37="",D37=0),0,C37/D37) -> 0 | F37: =E37 -> 0
B38: Emergency Fund — Cash | C38: =F32 -> 0 | D38: =C21 -> 0 | E38: =IF(OR(D38="",D38=0),0,C38/D38) -> 0 | F38: =E38 -> 0
B39: Retirement — TFSA + RRSP | C39: =F28+F30 -> 0 | D39: =C22 -> 0 | E39: =IF(OR(D39="",D39=0),0,C39/D39) -> 0 | F39: =E39 -> 0
B41: ACCOUNT MAP — HOW TO ORGANIZE YOUR ACCOUNTS
B42: • Registered accounts (TFSA / FHSA / RRSP) are per person, by law. Each person keeps their own — they cannot be merged, even for a couple.
B43: • Cash goals live in ONE savings account with labels (see Cash Buckets). The labels divide the same dollars — they do not need separate bank accounts.
B44: • One diversified fund per registered account keeps things simple and avoids holding the same investments twice in the same account.

Sheet Payday Tracker
B2: PAYDAY TRACKER — Tick It Off, Stay On Track
B3: Amounts pre-fill from Setup — change any single row if that pay was different. Monthly users: use 12 rows. Weekly users: use this sheet twice.
B4: Person names come from Setup. Red “⚠ OVER ROOM” = cumulative contributions for that account have passed the Jan 1 CRA room you entered — pause that account and see Room Tracker.
B6: Pay # | C6: Date | D6: Done ✓ | E6: P1 TFSA | F6: P1 FHSA | G6: P1 RRSP | H6: P2 TFSA | I6: P2 FHSA | J6: P2 RRSP | K6: Cash | L6: Pay Total | M6: Cumulative | N6: P1 TFSA Check | O6: P1 FHSA Check | P6: P1 RRSP Check | Q6: P2 TFSA Check | R6: P2 FHSA Check | S6: P2 RRSP Check
B7: 1 | E7: =IFERROR('Setup & Dashboard'!$E$14,0) -> 0 | F7: =IFERROR('Setup & Dashboard'!$E$15,0) -> 0 | G7: =IFERROR('Setup & Dashboard'!$E$16,0) -> 0 | H7: =IFERROR('Setup & Dashboard'!$H$14,0) -> 0 | I7: =IFERROR('Setup & Dashboard'!$H$15,0) -> 0 | J7: =IFERROR('Setup & Dashboard'!$H$16,0) -> 0 | K7: =IFERROR('Cash Buckets'!$E$13,0) -> 0 | L7: =SUM(E7:K7) -> 0 | M7: =L7 -> 0 | N7: =IF(OR('Setup & Dashboard'!$D$14="",'Setup & Dashboard'!$D$14=0),"",IF(SUM($E$7:E7)>'Setup & Dashboard'!$D$14,"⚠ OVER ROOM","")) | O7: =IF(OR('Setup & Dashboard'!$D$15="",'Setup & Dashboard'!$D$15=0),"",IF(SUM($F$7:F7)>'Setup & Dashboard'!$D$15,"⚠ OVER ROOM","")) | P7: =IF(OR('Setup & Dashboard'!$D$16="",'Setup & Dashboard'!$D$16=0),"",IF(SUM($G$7:G7)>'Setup & Dashboard'!$D$16,"⚠ OVER ROOM","")) | Q7: =IF(OR('Setup & Dashboard'!$G$14="",'Setup & Dashboard'!$G$14=0),"",IF(SUM($H$7:H7)>'Setup & Dashboard'!$G$14,"⚠ OVER ROOM","")) | R7: =IF(OR('Setup & Dashboard'!$G$15="",'Setup & Dashboard'!$G$15=0),"",IF(SUM($I$7:I7)>'Setup & Dashboard'!$G$15,"⚠ OVER ROOM","")) | S7: =IF(OR('Setup & Dashboard'!$G$16="",'Setup & Dashboard'!$G$16=0),"",IF(SUM($J$7:J7)>'Setup & Dashboard'!$G$16,"⚠ OVER ROOM",""))
B8: 2 | E8: =IFERROR('Setup & Dashboard'!$E$14,0) -> 0 | F8: =IFERROR('Setup & Dashboard'!$E$15,0) -> 0 | G8: =IFERROR('Setup & Dashboard'!$E$16,0) -> 0 | H8: =IFERROR('Setup & Dashboard'!$H$14,0) -> 0 | I8: =IFERROR('Setup & Dashboard'!$H$15,0) -> 0 | J8: =IFERROR('Setup & Dashboard'!$H$16,0) -> 0 | K8: =IFERROR('Cash Buckets'!$E$13,0) -> 0 | L8: =SUM(E8:K8) -> 0 | M8: =M7+L8 -> 0 | N8: =IF(OR('Setup & Dashboard'!$D$14="",'Setup & Dashboard'!$D$14=0),"",IF(SUM($E$7:E8)>'Setup & Dashboard'!$D$14,"⚠ OVER ROOM","")) | O8: =IF(OR('Setup & Dashboard'!$D$15="",'Setup & Dashboard'!$D$15=0),"",IF(SUM($F$7:F8)>'Setup & Dashboard'!$D$15,"⚠ OVER ROOM","")) | P8: =IF(OR('Setup & Dashboard'!$D$16="",'Setup & Dashboard'!$D$16=0),"",IF(SUM($G$7:G8)>'Setup & Dashboard'!$D$16,"⚠ OVER ROOM","")) | Q8: =IF(OR('Setup & Dashboard'!$G$14="",'Setup & Dashboard'!$G$14=0),"",IF(SUM($H$7:H8)>'Setup & Dashboard'!$G$14,"⚠ OVER ROOM","")) | R8: =IF(OR('Setup & Dashboard'!$G$15="",'Setup & Dashboard'!$G$15=0),"",IF(SUM($I$7:I8)>'Setup & Dashboard'!$G$15,"⚠ OVER ROOM","")) | S8: =IF(OR('Setup & Dashboard'!$G$16="",'Setup & Dashboard'!$G$16=0),"",IF(SUM($J$7:J8)>'Setup & Dashboard'!$G$16,"⚠ OVER ROOM",""))
B9: 3 | E9: =IFERROR('Setup & Dashboard'!$E$14,0) -> 0 | F9: =IFERROR('Setup & Dashboard'!$E$15,0) -> 0 | G9: =IFERROR('Setup & Dashboard'!$E$16,0) -> 0 | H9: =IFERROR('Setup & Dashboard'!$H$14,0) -> 0 | I9: =IFERROR('Setup & Dashboard'!$H$15,0) -> 0 | J9: =IFERROR('Setup & Dashboard'!$H$16,0) -> 0 | K9: =IFERROR('Cash Buckets'!$E$13,0) -> 0 | L9: =SUM(E9:K9) -> 0 | M9: =M8+L9 -> 0 | N9: =IF(OR('Setup & Dashboard'!$D$14="",'Setup & Dashboard'!$D$14=0),"",IF(SUM($E$7:E9)>'Setup & Dashboard'!$D$14,"⚠ OVER ROOM","")) | O9: =IF(OR('Setup & Dashboard'!$D$15="",'Setup & Dashboard'!$D$15=0),"",IF(SUM($F$7:F9)>'Setup & Dashboard'!$D$15,"⚠ OVER ROOM","")) | P9: =IF(OR('Setup & Dashboard'!$D$16="",'Setup & Dashboard'!$D$16=0),"",IF(SUM($G$7:G9)>'Setup & Dashboard'!$D$16,"⚠ OVER ROOM","")) | Q9: =IF(OR('Setup & Dashboard'!$G$14="",'Setup & Dashboard'!$G$14=0),"",IF(SUM($H$7:H9)>'Setup & Dashboard'!$G$14,"⚠ OVER ROOM","")) | R9: =IF(OR('Setup & Dashboard'!$G$15="",'Setup & Dashboard'!$G$15=0),"",IF(SUM($I$7:I9)>'Setup & Dashboard'!$G$15,"⚠ OVER ROOM","")) | S9: =IF(OR('Setup & Dashboard'!$G$16="",'Setup & Dashboard'!$G$16=0),"",IF(SUM($J$7:J9)>'Setup & Dashboard'!$G$16,"⚠ OVER ROOM",""))
B10: 4 | E10: =IFERROR('Setup & Dashboard'!$E$14,0) -> 0 | F10: =IFERROR('Setup & Dashboard'!$E$15,0) -> 0 | G10: =IFERROR('Setup & Dashboard'!$E$16,0) -> 0 | H10: =IFERROR('Setup & Dashboard'!$H$14,0) -> 0 | I10: =IFERROR('Setup & Dashboard'!$H$15,0) -> 0 | J10: =IFERROR('Setup & Dashboard'!$H$16,0) -> 0 | K10: =IFERROR('Cash Buckets'!$E$13,0) -> 0 | L10: =SUM(E10:K10) -> 0 | M10: =M9+L10 -> 0 | N10: =IF(OR('Setup & Dashboard'!$D$14="",'Setup & Dashboard'!$D$14=0),"",IF(SUM($E$7:E10)>'Setup & Dashboard'!$D$14,"⚠ OVER ROOM","")) | O10: =IF(OR('Setup & Dashboard'!$D$15="",'Setup & Dashboard'!$D$15=0),"",IF(SUM($F$7:F10)>'Setup & Dashboard'!$D$15,"⚠ OVER ROOM","")) | P10: =IF(OR('Setup & Dashboard'!$D$16="",'Setup & Dashboard'!$D$16=0),"",IF(SUM($G$7:G10)>'Setup & Dashboard'!$D$16,"⚠ OVER ROOM","")) | Q10: =IF(OR('Setup & Dashboard'!$G$14="",'Setup & Dashboard'!$G$14=0),"",IF(SUM($H$7:H10)>'Setup & Dashboard'!$G$14,"⚠ OVER ROOM","")) | R10: =IF(OR('Setup & Dashboard'!$G$15="",'Setup & Dashboard'!$G$15=0),"",IF(SUM($I$7:I10)>'Setup & Dashboard'!$G$15,"⚠ OVER ROOM","")) | S10: =IF(OR('Setup & Dashboard'!$G$16="",'Setup & Dashboard'!$G$16=0),"",IF(SUM($J$7:J10)>'Setup & Dashboard'!$G$16,"⚠ OVER ROOM",""))
B11: 5 | E11: =IFERROR('Setup & Dashboard'!$E$14,0) -> 0 | F11: =IFERROR('Setup & Dashboard'!$E$15,0) -> 0 | G11: =IFERROR('Setup & Dashboard'!$E$16,0) -> 0 | H11: =IFERROR('Setup & Dashboard'!$H$14,0) -> 0 | I11: =IFERROR('Setup & Dashboard'!$H$15,0) -> 0 | J11: =IFERROR('Setup & Dashboard'!$H$16,0) -> 0 | K11: =IFERROR('Cash Buckets'!$E$13,0) -> 0 | L11: =SUM(E11:K11) -> 0 | M11: =M10+L11 -> 0 | N11: =IF(OR('Setup & Dashboard'!$D$14="",'Setup & Dashboard'!$D$14=0),"",IF(SUM($E$7:E11)>'Setup & Dashboard'!$D$14,"⚠ OVER ROOM","")) | O11: =IF(OR('Setup & Dashboard'!$D$15="",'Setup & Dashboard'!$D$15=0),"",IF(SUM($F$7:F11)>'Setup & Dashboard'!$D$15,"⚠ OVER ROOM","")) | P11: =IF(OR('Setup & Dashboard'!$D$16="",'Setup & Dashboard'!$D$16=0),"",IF(SUM($G$7:G11)>'Setup & Dashboard'!$D$16,"⚠ OVER ROOM","")) | Q11: =IF(OR('Setup & Dashboard'!$G$14="",'Setup & Dashboard'!$G$14=0),"",IF(SUM($H$7:H11)>'Setup & Dashboard'!$G$14,"⚠ OVER ROOM","")) | R11: =IF(OR('Setup & Dashboard'!$G$15="",'Setup & Dashboard'!$G$15=0),"",IF(SUM($I$7:I11)>'Setup & Dashboard'!$G$15,"⚠ OVER ROOM","")) | S11: =IF(OR('Setup & Dashboard'!$G$16="",'Setup & Dashboard'!$G$16=0),"",IF(SUM($J$7:J11)>'Setup & Dashboard'!$G$16,"⚠ OVER ROOM",""))
B12: 6 | E12: =IFERROR('Setup & Dashboard'!$E$14,0) -> 0 | F12: =IFERROR('Setup & Dashboard'!$E$15,0) -> 0 | G12: =IFERROR('Setup & Dashboard'!$E$16,0) -> 0 | H12: =IFERROR('Setup & Dashboard'!$H$14,0) -> 0 | I12: =IFERROR('Setup & Dashboard'!$H$15,0) -> 0 | J12: =IFERROR('Setup & Dashboard'!$H$16,0) -> 0 | K12: =IFERROR('Cash Buckets'!$E$13,0) -> 0 | L12: =SUM(E12:K12) -> 0 | M12: =M11+L12 -> 0 | N12: =IF(OR('Setup & Dashboard'!$D$14="",'Setup & Dashboard'!$D$14=0),"",IF(SUM($E$7:E12)>'Setup & Dashboard'!$D$14,"⚠ OVER ROOM","")) | O12: =IF(OR('Setup & Dashboard'!$D$15="",'Setup & Dashboard'!$D$15=0),"",IF(SUM($F$7:F12)>'Setup & Dashboard'!$D$15,"⚠ OVER ROOM","")) | P12: =IF(OR('Setup & Dashboard'!$D$16="",'Setup & Dashboard'!$D$16=0),"",IF(SUM($G$7:G12)>'Setup & Dashboard'!$D$16,"⚠ OVER ROOM","")) | Q12: =IF(OR('Setup & Dashboard'!$G$14="",'Setup & Dashboard'!$G$14=0),"",IF(SUM($H$7:H12)>'Setup & Dashboard'!$G$14,"⚠ OVER ROOM","")) | R12: =IF(OR('Setup & Dashboard'!$G$15="",'Setup & Dashboard'!$G$15=0),"",IF(SUM($I$7:I12)>'Setup & Dashboard'!$G$15,"⚠ OVER ROOM","")) | S12: =IF(OR('Setup & Dashboard'!$G$16="",'Setup & Dashboard'!$G$16=0),"",IF(SUM($J$7:J12)>'Setup & Dashboard'!$G$16,"⚠ OVER ROOM",""))
B13: 7 | E13: =IFERROR('Setup & Dashboard'!$E$14,0) -> 0 | F13: =IFERROR('Setup & Dashboard'!$E$15,0) -> 0 | G13: =IFERROR('Setup & Dashboard'!$E$16,0) -> 0 | H13: =IFERROR('Setup & Dashboard'!$H$14,0) -> 0 | I13: =IFERROR('Setup & Dashboard'!$H$15,0) -> 0 | J13: =IFERROR('Setup & Dashboard'!$H$16,0) -> 0 | K13: =IFERROR('Cash Buckets'!$E$13,0) -> 0 | L13: =SUM(E13:K13) -> 0 | M13: =M12+L13 -> 0 | N13: =IF(OR('Setup & Dashboard'!$D$14="",'Setup & Dashboard'!$D$14=0),"",IF(SUM($E$7:E13)>'Setup & Dashboard'!$D$14,"⚠ OVER ROOM","")) | O13: =IF(OR('Setup & Dashboard'!$D$15="",'Setup & Dashboard'!$D$15=0),"",IF(SUM($F$7:F13)>'Setup & Dashboard'!$D$15,"⚠ OVER ROOM","")) | P13: =IF(OR('Setup & Dashboard'!$D$16="",'Setup & Dashboard'!$D$16=0),"",IF(SUM($G$7:G13)>'Setup & Dashboard'!$D$16,"⚠ OVER ROOM","")) | Q13: =IF(OR('Setup & Dashboard'!$G$14="",'Setup & Dashboard'!$G$14=0),"",IF(SUM($H$7:H13)>'Setup & Dashboard'!$G$14,"⚠ OVER ROOM","")) | R13: =IF(OR('Setup & Dashboard'!$G$15="",'Setup & Dashboard'!$G$15=0),"",IF(SUM($I$7:I13)>'Setup & Dashboard'!$G$15,"⚠ OVER ROOM","")) | S13: =IF(OR('Setup & Dashboard'!$G$16="",'Setup & Dashboard'!$G$16=0),"",IF(SUM($J$7:J13)>'Setup & Dashboard'!$G$16,"⚠ OVER ROOM",""))
B14: 8 | E14: =IFERROR('Setup & Dashboard'!$E$14,0) -> 0 | F14: =IFERROR('Setup & Dashboard'!$E$15,0) -> 0 | G14: =IFERROR('Setup & Dashboard'!$E$16,0) -> 0 | H14: =IFERROR('Setup & Dashboard'!$H$14,0) -> 0 | I14: =IFERROR('Setup & Dashboard'!$H$15,0) -> 0 | J14: =IFERROR('Setup & Dashboard'!$H$16,0) -> 0 | K14: =IFERROR('Cash Buckets'!$E$13,0) -> 0 | L14: =SUM(E14:K14) -> 0 | M14: =M13+L14 -> 0 | N14: =IF(OR('Setup & Dashboard'!$D$14="",'Setup & Dashboard'!$D$14=0),"",IF(SUM($E$7:E14)>'Setup & Dashboard'!$D$14,"⚠ OVER ROOM","")) | O14: =IF(OR('Setup & Dashboard'!$D$15="",'Setup & Dashboard'!$D$15=0),"",IF(SUM($F$7:F14)>'Setup & Dashboard'!$D$15,"⚠ OVER ROOM","")) | P14: =IF(OR('Setup & Dashboard'!$D$16="",'Setup & Dashboard'!$D$16=0),"",IF(SUM($G$7:G14)>'Setup & Dashboard'!$D$16,"⚠ OVER ROOM","")) | Q14: =IF(OR('Setup & Dashboard'!$G$14="",'Setup & Dashboard'!$G$14=0),"",IF(SUM($H$7:H14)>'Setup & Dashboard'!$G$14,"⚠ OVER ROOM","")) | R14: =IF(OR('Setup & Dashboard'!$G$15="",'Setup & Dashboard'!$G$15=0),"",IF(SUM($I$7:I14)>'Setup & Dashboard'!$G$15,"⚠ OVER ROOM","")) | S14: =IF(OR('Setup & Dashboard'!$G$16="",'Setup & Dashboard'!$G$16=0),"",IF(SUM($J$7:J14)>'Setup & Dashboard'!$G$16,"⚠ OVER ROOM",""))
B15: 9 | E15: =IFERROR('Setup & Dashboard'!$E$14,0) -> 0 | F15: =IFERROR('Setup & Dashboard'!$E$15,0) -> 0 | G15: =IFERROR('Setup & Dashboard'!$E$16,0) -> 0 | H15: =IFERROR('Setup & Dashboard'!$H$14,0) -> 0 | I15: =IFERROR('Setup & Dashboard'!$H$15,0) -> 0 | J15: =IFERROR('Setup & Dashboard'!$H$16,0) -> 0 | K15: =IFERROR('Cash Buckets'!$E$13,0) -> 0 | L15: =SUM(E15:K15) -> 0 | M15: =M14+L15 -> 0 | N15: =IF(OR('Setup & Dashboard'!$D$14="",'Setup & Dashboard'!$D$14=0),"",IF(SUM($E$7:E15)>'Setup & Dashboard'!$D$14,"⚠ OVER ROOM","")) | O15: =IF(OR('Setup & Dashboard'!$D$15="",'Setup & Dashboard'!$D$15=0),"",IF(SUM($F$7:F15)>'Setup & Dashboard'!$D$15,"⚠ OVER ROOM","")) | P15: =IF(OR('Setup & Dashboard'!$D$16="",'Setup & Dashboard'!$D$16=0),"",IF(SUM($G$7:G15)>'Setup & Dashboard'!$D$16,"⚠ OVER ROOM","")) | Q15: =IF(OR('Setup & Dashboard'!$G$14="",'Setup & Dashboard'!$G$14=0),"",IF(SUM($H$7:H15)>'Setup & Dashboard'!$G$14,"⚠ OVER ROOM","")) | R15: =IF(OR('Setup & Dashboard'!$G$15="",'Setup & Dashboard'!$G$15=0),"",IF(SUM($I$7:I15)>'Setup & Dashboard'!$G$15,"⚠ OVER ROOM","")) | S15: =IF(OR('Setup & Dashboard'!$G$16="",'Setup & Dashboard'!$G$16=0),"",IF(SUM($J$7:J15)>'Setup & Dashboard'!$G$16,"⚠ OVER ROOM",""))
B16: 10 | E16: =IFERROR('Setup & Dashboard'!$E$14,0) -> 0 | F16: =IFERROR('Setup & Dashboard'!$E$15,0) -> 0 | G16: =IFERROR('Setup & Dashboard'!$E$16,0) -> 0 | H16: =IFERROR('Setup & Dashboard'!$H$14,0) -> 0 | I16: =IFERROR('Setup & Dashboard'!$H$15,0) -> 0 | J16: =IFERROR('Setup & Dashboard'!$H$16,0) -> 0 | K16: =IFERROR('Cash Buckets'!$E$13,0) -> 0 | L16: =SUM(E16:K16) -> 0 | M16: =M15+L16 -> 0 | N16: =IF(OR('Setup & Dashboard'!$D$14="",'Setup & Dashboard'!$D$14=0),"",IF(SUM($E$7:E16)>'Setup & Dashboard'!$D$14,"⚠ OVER ROOM","")) | O16: =IF(OR('Setup & Dashboard'!$D$15="",'Setup & Dashboard'!$D$15=0),"",IF(SUM($F$7:F16)>'Setup & Dashboard'!$D$15,"⚠ OVER ROOM","")) | P16: =IF(OR('Setup & Dashboard'!$D$16="",'Setup & Dashboard'!$D$16=0),"",IF(SUM($G$7:G16)>'Setup & Dashboard'!$D$16,"⚠ OVER ROOM","")) | Q16: =IF(OR('Setup & Dashboard'!$G$14="",'Setup & Dashboard'!$G$14=0),"",IF(SUM($H$7:H16)>'Setup & Dashboard'!$G$14,"⚠ OVER ROOM","")) | R16: =IF(OR('Setup & Dashboard'!$G$15="",'Setup & Dashboard'!$G$15=0),"",IF(SUM($I$7:I16)>'Setup & Dashboard'!$G$15,"⚠ OVER ROOM","")) | S16: =IF(OR('Setup & Dashboard'!$G$16="",'Setup & Dashboard'!$G$16=0),"",IF(SUM($J$7:J16)>'Setup & Dashboard'!$G$16,"⚠ OVER ROOM",""))
B17: 11 | E17: =IFERROR('Setup & Dashboard'!$E$14,0) -> 0 | F17: =IFERROR('Setup & Dashboard'!$E$15,0) -> 0 | G17: =IFERROR('Setup & Dashboard'!$E$16,0) -> 0 | H17: =IFERROR('Setup & Dashboard'!$H$14,0) -> 0 | I17: =IFERROR('Setup & Dashboard'!$H$15,0) -> 0 | J17: =IFERROR('Setup & Dashboard'!$H$16,0) -> 0 | K17: =IFERROR('Cash Buckets'!$E$13,0) -> 0 | L17: =SUM(E17:K17) -> 0 | M17: =M16+L17 -> 0 | N17: =IF(OR('Setup & Dashboard'!$D$14="",'Setup & Dashboard'!$D$14=0),"",IF(SUM($E$7:E17)>'Setup & Dashboard'!$D$14,"⚠ OVER ROOM","")) | O17: =IF(OR('Setup & Dashboard'!$D$15="",'Setup & Dashboard'!$D$15=0),"",IF(SUM($F$7:F17)>'Setup & Dashboard'!$D$15,"⚠ OVER ROOM","")) | P17: =IF(OR('Setup & Dashboard'!$D$16="",'Setup & Dashboard'!$D$16=0),"",IF(SUM($G$7:G17)>'Setup & Dashboard'!$D$16,"⚠ OVER ROOM","")) | Q17: =IF(OR('Setup & Dashboard'!$G$14="",'Setup & Dashboard'!$G$14=0),"",IF(SUM($H$7:H17)>'Setup & Dashboard'!$G$14,"⚠ OVER ROOM","")) | R17: =IF(OR('Setup & Dashboard'!$G$15="",'Setup & Dashboard'!$G$15=0),"",IF(SUM($I$7:I17)>'Setup & Dashboard'!$G$15,"⚠ OVER ROOM","")) | S17: =IF(OR('Setup & Dashboard'!$G$16="",'Setup & Dashboard'!$G$16=0),"",IF(SUM($J$7:J17)>'Setup & Dashboard'!$G$16,"⚠ OVER ROOM",""))
B18: 12 | E18: =IFERROR('Setup & Dashboard'!$E$14,0) -> 0 | F18: =IFERROR('Setup & Dashboard'!$E$15,0) -> 0 | G18: =IFERROR('Setup & Dashboard'!$E$16,0) -> 0 | H18: =IFERROR('Setup & Dashboard'!$H$14,0) -> 0 | I18: =IFERROR('Setup & Dashboard'!$H$15,0) -> 0 | J18: =IFERROR('Setup & Dashboard'!$H$16,0) -> 0 | K18: =IFERROR('Cash Buckets'!$E$13,0) -> 0 | L18: =SUM(E18:K18) -> 0 | M18: =M17+L18 -> 0 | N18: =IF(OR('Setup & Dashboard'!$D$14="",'Setup & Dashboard'!$D$14=0),"",IF(SUM($E$7:E18)>'Setup & Dashboard'!$D$14,"⚠ OVER ROOM","")) | O18: =IF(OR('Setup & Dashboard'!$D$15="",'Setup & Dashboard'!$D$15=0),"",IF(SUM($F$7:F18)>'Setup & Dashboard'!$D$15,"⚠ OVER ROOM","")) | P18: =IF(OR('Setup & Dashboard'!$D$16="",'Setup & Dashboard'!$D$16=0),"",IF(SUM($G$7:G18)>'Setup & Dashboard'!$D$16,"⚠ OVER ROOM","")) | Q18: =IF(OR('Setup & Dashboard'!$G$14="",'Setup & Dashboard'!$G$14=0),"",IF(SUM($H$7:H18)>'Setup & Dashboard'!$G$14,"⚠ OVER ROOM","")) | R18: =IF(OR('Setup & Dashboard'!$G$15="",'Setup & Dashboard'!$G$15=0),"",IF(SUM($I$7:I18)>'Setup & Dashboard'!$G$15,"⚠ OVER ROOM","")) | S18: =IF(OR('Setup & Dashboard'!$G$16="",'Setup & Dashboard'!$G$16=0),"",IF(SUM($J$7:J18)>'Setup & Dashboard'!$G$16,"⚠ OVER ROOM",""))
B19: 13 | E19: =IFERROR('Setup & Dashboard'!$E$14,0) -> 0 | F19: =IFERROR('Setup & Dashboard'!$E$15,0) -> 0 | G19: =IFERROR('Setup & Dashboard'!$E$16,0) -> 0 | H19: =IFERROR('Setup & Dashboard'!$H$14,0) -> 0 | I19: =IFERROR('Setup & Dashboard'!$H$15,0) -> 0 | J19: =IFERROR('Setup & Dashboard'!$H$16,0) -> 0 | K19: =IFERROR('Cash Buckets'!$E$13,0) -> 0 | L19: =SUM(E19:K19) -> 0 | M19: =M18+L19 -> 0 | N19: =IF(OR('Setup & Dashboard'!$D$14="",'Setup & Dashboard'!$D$14=0),"",IF(SUM($E$7:E19)>'Setup & Dashboard'!$D$14,"⚠ OVER ROOM","")) | O19: =IF(OR('Setup & Dashboard'!$D$15="",'Setup & Dashboard'!$D$15=0),"",IF(SUM($F$7:F19)>'Setup & Dashboard'!$D$15,"⚠ OVER ROOM","")) | P19: =IF(OR('Setup & Dashboard'!$D$16="",'Setup & Dashboard'!$D$16=0),"",IF(SUM($G$7:G19)>'Setup & Dashboard'!$D$16,"⚠ OVER ROOM","")) | Q19: =IF(OR('Setup & Dashboard'!$G$14="",'Setup & Dashboard'!$G$14=0),"",IF(SUM($H$7:H19)>'Setup & Dashboard'!$G$14,"⚠ OVER ROOM","")) | R19: =IF(OR('Setup & Dashboard'!$G$15="",'Setup & Dashboard'!$G$15=0),"",IF(SUM($I$7:I19)>'Setup & Dashboard'!$G$15,"⚠ OVER ROOM","")) | S19: =IF(OR('Setup & Dashboard'!$G$16="",'Setup & Dashboard'!$G$16=0),"",IF(SUM($J$7:J19)>'Setup & Dashboard'!$G$16,"⚠ OVER ROOM",""))
... B32: 26 | E32: =IFERROR('Setup & Dashboard'!$E$14,0) -> 0 | F32: =IFERROR('Setup & Dashboard'!$E$15,0) -> 0 | G32: =IFERROR('Setup & Dashboard'!$E$16,0) -> 0 | H32: =IFERROR('Setup & Dashboard'!$H$14,0) -> 0 | I32: =IFERROR('Setup & Dashboard'!$H$15,0) -> 0 | J32: =IFERROR('Setup & Dashboard'!$H$16,0) -> 0 | K32: =IFERROR('Cash Buckets'!$E$13,0) -> 0 | L32: =SUM(E32:K32) -> 0 | M32: =M31+L32 -> 0 | N32: =IF(OR('Setup & Dashboard'!$D$14="",'Setup & Dashboard'!$D$14=0),"",IF(SUM($E$7:E32)>'Setup & Dashboard'!$D$14,"⚠ OVER ROOM","")) | O32: =IF(OR('Setup & Dashboard'!$D$15="",'Setup & Dashboard'!$D$15=0),"",IF(SUM($F$7:F32)>'Setup & Dashboard'!$D$15,"⚠ OVER ROOM","")) | P32: =IF(OR('Setup & Dashboard'!$D$16="",'Setup & Dashboard'!$D$16=0),"",IF(SUM($G$7:G32)>'Setup & Dashboard'!$D$16,"⚠ OVER ROOM","")) | Q32: =IF(OR('Setup & Dashboard'!$G$14="",'Setup & Dashboard'!$G$14=0),"",IF(SUM($H$7:H32)>'Setup & Dashboard'!$G$14,"⚠ OVER ROOM","")) | R32: =IF(OR('Setup & Dashboard'!$G$15="",'Setup & Dashboard'!$G$15=0),"",IF(SUM($I$7:I32)>'Setup & Dashboard'!$G$15,"⚠ OVER ROOM","")) | S32: =IF(OR('Setup & Dashboard'!$G$16="",'Setup & Dashboard'!$G$16=0),"",IF(SUM($J$7:J32)>'Setup & Dashboard'!$G$16,"⚠ OVER ROOM",""))
B33: TOTAL | E33: =SUM(E7:E32) -> 0 | F33: =SUM(F7:F32) -> 0 | G33: =SUM(G7:G32) -> 0 | H33: =SUM(H7:H32) -> 0 | I33: =SUM(I7:I32) -> 0 | J33: =SUM(J7:J32) -> 0 | K33: =SUM(K7:K32) -> 0 | L33: =SUM(L7:L32) -> 0
B35: If a check flags OVER ROOM mid-year, stop contributions to that account, redirect to the next account in the Rules waterfall, and confirm room in CRA My Account.

Sheet Room Tracker
B2: ROOM TRACKER — Never Over-Contribute Again
B3: Everything here calculates from Setup + Payday Tracker. Names update from Setup. Confirm your real room in CRA My Account.
B5: Metric | C5: Person 1 | D5: Person 2 | E5: How to Read It
B6: FHSA — CRA room on Jan 1 | C6: =IFERROR('Setup & Dashboard'!D15,0) -> 0 | D6: =IFERROR('Setup & Dashboard'!G15,0) -> 0 | E6: Enter this in Setup.
B7: FHSA — Contributed so far (Payday Tracker) | C7: =SUM('Payday Tracker'!F7:F32) -> 0 | D7: =SUM('Payday Tracker'!I7:I32) -> 0 | E7: All Payday FHSA rows added up.
B8: FHSA — Room left | C8: =C6-C7 -> 0 | D8: =D6-D7 -> 0 | E8: Negative = over room. Stop and check CRA.
B9: FHSA — Starting balance | C9: =IFERROR('Setup & Dashboard'!C15,0) -> 0 | D9: =IFERROR('Setup & Dashboard'!F15,0) -> 0
B10: FHSA — Projected balance (starting + contributed) | C10: =C9+C7 -> 0 | D10: =D9+D7 -> 0
B11: FHSA — Progress to $40,000 lifetime cap | C11: =IF(OR('Setup & Dashboard'!$C$23="",'Setup & Dashboard'!$C$23=0),0,C10/'Setup & Dashboard'!$C$23) -> 0 | D11: =IF(OR('Setup & Dashboard'!$C$23="",'Setup & Dashboard'!$C$23=0),0,D10/'Setup & Dashboard'!$C$23) -> 0 | E11: Cap is per person, lifetime.
B12: FHSA — Planned per pay | C12: =IFERROR('Setup & Dashboard'!E15,0) -> 0 | D12: =IFERROR('Setup & Dashboard'!H15,0) -> 0
B13: FHSA — Pays of room left (from Jan 1) | C13: =IF(OR(C12="",C12=0,C6="",C6=0),"—",ROUNDUP(C6/C12,0)) -> — | D13: =IF(OR(D12="",D12=0,D6="",D6=0),"—",ROUNDUP(D6/D12,0)) -> — | E13: Jan 1 room ÷ per-pay amount, rounded up.
B14: FHSA — Approx. pay # when room runs out | C14: =C13 -> — | D14: =D13 -> — | E14: On this pay, switch FHSA → TFSA (see rule below).
B16: TFSA — CRA room on Jan 1 | C16: =IFERROR('Setup & Dashboard'!D14,0) -> 0 | D16: =IFERROR('Setup & Dashboard'!G14,0) -> 0
B17: TFSA — Contributed so far | C17: =SUM('Payday Tracker'!E7:E32) -> 0 | D17: =SUM('Payday Tracker'!H7:H32) -> 0
B18: TFSA — Room left | C18: =C16-C17 -> 0 | D18: =D16-D17 -> 0
B20: RRSP — CRA room on Jan 1 | C20: =IFERROR('Setup & Dashboard'!D16,0) -> 0 | D20: =IFERROR('Setup & Dashboard'!G16,0) -> 0
B21: RRSP — Contributed so far | C21: =SUM('Payday Tracker'!G7:G32) -> 0 | D21: =SUM('Payday Tracker'!J7:J32) -> 0
B22: RRSP — Room left | C22: =C20-C21 -> 0 | D22: =D20-D21 -> 0
B23: RRSP — Starting balance | C23: =IFERROR('Setup & Dashboard'!C16,0) -> 0 | D23: =IFERROR('Setup & Dashboard'!F16,0) -> 0
B24: RRSP — Projected balance | C24: =C23+C21 -> 0 | D24: =D23+D21 -> 0
B25: RRSP — Progress to Home Buyers' Plan target | C25: =IF(OR('Setup & Dashboard'!$C$24="",'Setup & Dashboard'!$C$24=0),0,C24/'Setup & Dashboard'!$C$24) -> 0 | D25: =IF(OR('Setup & Dashboard'!$C$24="",'Setup & Dashboard'!$C$24=0),0,D24/'Setup & Dashboard'!$C$24) -> 0 | E25: HBP target is editable in Setup (default $60,000).
B27: THE SWITCH RULE — IN PLAIN ENGLISH
B28: • When FHSA room runs out, STOP FHSA contributions. Redirect that same per-pay amount to TFSA instead — do not increase your total, just change the account.
B29: • Keep redirecting to TFSA until Jan 1, when new FHSA room may arrive. Then re-check CRA My Account, update Setup, and restart.
B30: • If TFSA room also runs out, move down the waterfall: FHSA (to room) → TFSA → RRSP → Cash. See Rules.

Sheet Cash Buckets
B2: CASH BUCKETS — One Account, Clear Labels
B3: Cash is never invested. All buckets live in ONE savings account — the labels below divide the same pot so a car repair never steals your vacation money.
B4: Yellow = edit. Defaults are suggestions only — set targets that fit your life. Starting allocations together should add up to your cash pot in Setup (C10).
B6: Bucket | C6: Target | D6: Starting Allocation | E6: Per Pay | F6: Annual | G6: Projected Dec 31 | H6: Progress | I6: Notes
B7: Core Emergency | F7: =IFERROR(E7*'Setup & Dashboard'!$C$7,0) -> 0 | G7: =IFERROR(D7,0)+F7 -> 0 | H7: =IF(OR(C7="",C7=0),0,G7/C7) -> 0 | I7: Job loss / income gap — build this first.
B8: Car Repairs | F8: =IFERROR(E8*'Setup & Dashboard'!$C$7,0) -> 0 | G8: =IFERROR(D8,0)+F8 -> 0 | H8: =IF(OR(C8="",C8=0),0,G8/C8) -> 0 | I8: Repairs, tires, deductible.
B9: Family | F9: =IFERROR(E9*'Setup & Dashboard'!$C$7,0) -> 0 | G9: =IFERROR(D9,0)+F9 -> 0 | H9: =IF(OR(C9="",C9=0),0,G9/C9) -> 0 | I9: Urgent family help / flights.
B10: Vacation | F10: =IFERROR(E10*'Setup & Dashboard'!$C$7,0) -> 0 | G10: =IFERROR(D10,0)+F10 -> 0 | H10: =IF(OR(C10="",C10=0),0,G10/C10) -> 0 | I10: Save it, spend it guilt-free, rebuild it.
B11: Custom 1 — name your own | F11: =IFERROR(E11*'Setup & Dashboard'!$C$7,0) -> 0 | G11: =IFERROR(D11,0)+F11 -> 0 | H11: =IF(OR(C11="",C11=0),0,G11/C11) -> 0
B12: Custom 2 — name your own | F12: =IFERROR(E12*'Setup & Dashboard'!$C$7,0) -> 0 | G12: =IFERROR(D12,0)+F12 -> 0 | H12: =IF(OR(C12="",C12=0),0,G12/C12) -> 0
B13: TOTAL — Cash Buckets | C13: =SUM(C7:C12) -> 0 | D13: =SUM(D7:D12) -> 0 | E13: =SUM(E7:E12) -> 0 | F13: =SUM(F7:F12) -> 0 | G13: =SUM(G7:G12) -> 0 | H13: =IF(OR(C13="",C13=0),0,G13/C13) -> 0 | I13: Check: Starting total should match Setup cash pot.
B15: Rule: Never invest money you will need in under 2 years. Once Core Emergency hits its target, redirect that per-pay amount to TFSA (see Rules).

Sheet Rules
B2: RULES — The Pay Yourself First System
B3: Simple rules, followed every payday, beat complicated plans followed sometimes.
B5: 1 PAY YOURSELF FIRST
B6: On payday, contributions leave first — before spending. Set up automatic transfers in your bank / broker app for the day after payday, in the amounts from Setup.
B9: 2 ONE DIVERSIFIED FUND PER ACCOUNT
B10: Keep each registered account simple: one diversified fund per account, rather than several overlapping funds that hold the same things. Simplicity is what makes automation stick.
B13: 3 THE WATERFALL FOR EXTRA MONEY
B14: Bonus, tax refund, or a raise? Send extra money in this order: ① FHSA until room runs out → ② TFSA → ③ RRSP → ④ Cash buckets until targets are met.
B17: 4 ROOM BEFORE AMOUNT
B18: Never guess room. Confirm TFSA / FHSA / RRSP room in CRA My Account — especially before December pays — and update Setup whenever CRA updates your numbers.
B21: 5 CASH STAYS CASH
B22: Emergency, car, family and vacation money stays in a savings account, never invested. Its job is to be there, not to grow.
... B29: Reminder: This tracker is an organization and education tool, not financial, tax, or investment advice. See Start Here for the full disclaimer.

Sheet Example
B2: EXAMPLE — Sample Data Only
B3: EXAMPLE — SAMPLE DATA ONLY, DELETE OR IGNORE THIS SHEET • Fictional couple: Alex & Sam • Round numbers, for illustration
B4: This is what a completed year looks like. Your real numbers go in Setup & Dashboard — not here.
B6: ALEX & SAM — SETUP SNAPSHOT (SAMPLE YEAR, 26 BIWEEKLY PAYS)
B7: Account | C7: Alex Starting | D7: Alex Room | E7: Alex / Pay | F7: Sam Starting | G7: Sam Room | H7: Sam / Pay
B8: TFSA | C8: 5000 | D8: 12000 | E8: 200 | F8: 3000 | G8: 9000 | H8: 150
B9: FHSA | C9: 2000 | D9: 16000 | E9: 300 | F9: 1000 | G9: 16000 | H9: 250
B10: RRSP | C10: 8000 | D10: 25000 | E10: 100 | F10: 4000 | G10: 18000 | H10: 100
B12: ALEX & SAM — PROJECTED YEAR (SAMPLE, CONTRIBUTIONS ONLY)
B13: Account | C13: Alex Annual | D13: Sam Annual | E13: Household Annual | F13: Notes
B14: TFSA | C14: =E8*26 -> 5200 | D14: =H8*26 -> 3900 | E14: =C14+D14 -> 9100 | F14: =C8+F8+E14 -> 17100
B15: FHSA | C15: =E9*26 -> 7800 | D15: =H9*26 -> 6500 | E15: =C15+D15 -> 14300 | F15: =C9+F9+E15 -> 17300 | G15: FHSA room lasts all year
B16: RRSP | C16: =E10*26 -> 2600 | D16: =H10*26 -> 2600 | E16: =C16+D16 -> 5200 | F16: =C10+F10+E16 -> 17200
B17: TOTAL — Registered | C17: =SUM(C14:C16) -> 15600 | D17: =SUM(D14:D16) -> 13000 | E17: =SUM(E14:E16) -> 28600 | F17: =SUM(F14:F16) -> 51600 | G17: $28,600 / year household
B19: SAMPLE PAYDAY ROWS (FIRST 4 PAYS)
B20: Pay # | C20: Alex TFSA | D20: Alex FHSA | E20: Alex RRSP | F20: Sam TFSA | G20: Sam FHSA | H20: Sam RRSP
B21: Pay 1 | C21: 200 | D21: 300 | E21: 100 | F21: 150 | G21: 250 | H21: 100
B22: Pay 2 | C22: 200 | D22: 300 | E22: 100 | F22: 150 | G22: 250 | H22: 100
B23: Pay 3 | C23: 200 | D23: 300 | E23: 100 | F23: 150 | G23: 250 | H23: 100
B24: Pay 4 | C24: 200 | D24: 300 | E24: 100 | F24: 150 | G24: 250 | H24: 100
B26: Cash sample: Alex & Sam also save $250 / pay into cash buckets ($100 Core Emergency + $50 Car + $50 Family + $50 Vacation) = $6,500 / year, in one savings account.
B27: FHSA check (sample): Alex has $16,000 room ÷ $300 / pay = 54 pays of room — more than a full year, so no switch is needed this year.
